osm_flex/__init__.py
osm_flex/clip.py
osm_flex/config.py
osm_flex/download.py
osm_flex/extract.py
osm_flex/osmconf.ini
osm_flex/simplify.py
osm_flex-1.1.1.dist-info/AUTHORS.md
osm_flex-1.1.1.dist-info/LICENSE
osm_flex-1.1.1.dist-info/METADATA
osm_flex-1.1.1.dist-info/WHEEL
osm_flex-1.1.1.dist-info/top_level.txt
osm_flex-1.1.1.dist-info/RECORD
