Metadata-Version: 2.1
Name: osm-flex
Version: 1.1.1
Summary: Python package for flexible data extraction from OpenStreetMap
Maintainer-email: Elco Koks <elco.koks@vu.nl>
License: GPL-3.0
Project-URL: Repository, https://github.com/osm-flex/osm-flex
Project-URL: Bug Tracker, https://github.com/osm-flex/osm-flex/issues
Keywords: OpenStreetMap
Classifier: Development Status :: 4 - Beta
Classifier: Intended Audience :: Science/Research
Classifier: Programming Language :: Python :: 3.9
Classifier: Topic :: Scientific/Engineering :: GIS
Requires-Python: >=3.9
License-File: LICENSE
License-File: AUTHORS.md
Requires-Dist: cartopy
Requires-Dist: geopandas
Requires-Dist: gdal
Requires-Dist: numpy
Requires-Dist: shapely >=2.0
Requires-Dist: pandas
Requires-Dist: tqdm
Provides-Extra: docs
Requires-Dist: jupyter ; extra == 'docs'
Provides-Extra: tests
Requires-Dist: pytest ; extra == 'tests'
